[
  {
    "name": "invoice template - blue theme",
    "description": "Default invoice template with blue theme",
    "markdown_content": "\n---\ncss: invoice.css\ngeometry: margin=1in\n---\n\n:::::::::::::::::::: invoice-header\n\n# {{company_name}}\n\n{{company_address}}  \n{{company_city}}, {{company_state}} {{company_zip}}  \n{{company_email}}  \n{{company_phone}}\n\n**Invoice No:** INV-{{invoice_number}}\n\n::::::::::::::::::::\n\n---\n\n:::::::::::::::::::: parties\n\n### Bill To\n\n**{{billing_name}}**  \n{{billing_address}}  \n{{billing_city}}, {{billing_state}} {{billing_zip}}  \n{{billing_email}}  \n{{billing_phone}}\n\n---\n\n### Ship To\n\n**{{shipping_name}}**  \n{{shipping_address}}  \n{{shipping_city}}, {{shipping_state}} {{shipping_zip}}\n\nSame as billing address\n\n::::::::::::::::::::\n\n---\n\n:::::::::::::::::::: meta\n\n| Invoice Date | Due Date | Payment Terms |\n|--------------|----------|---------------|\n| {{issue_date}} | {{due_date}} | {{payment_terms}} |\n\n::::::::::::::::::::\n\n---\n\n## 🧾 Invoice Items\n\n| Description | Quantity | Unit Price | Amount |\n|-------------|----------|------------|--------|\n{{line_items}}\n\n---\n\n:::::::::::::::::::: totals\n\n**Subtotal:** {{subtotal}}  \n**Tax (10%):** {{tax}}\n\n### **Total Due: {{total}}**\n\n::::::::::::::::::::\n\n---\n\n:::::::::::::::::::: notes\n\n### Payment Instructions\n\n{{notes}}\n\n::::::::::::::::::::\n\n---\n\n:::::::::::::::::::: footer\n\nThank you for your business!  \nFor invoice questions: **{{company_email}}**\n\n::::::::::::::::::::\n\n\n",
    "css_content": "body {\n  font-family: \"Segoe UI\", system-ui, sans-serif;\n  background: #ffffff;\n  color: #333;\n}\n/* HEADER */\n.invoice-header {\n  background: linear-gradient(135deg, #667eea, #764ba2);\n  color: white;\n  padding: 40px;\n  border-radius: 16px;\n  margin-bottom: 30px;\n}\n.invoice-header h1 {\n  font-size: 32px;\n  margin-bottom: 10px;\n}\n.invoice-header h2 {\n  font-size: 40px;\n  text-align: right;\n}\n/* BILL / SHIP */\n.parties {\n  display: flex;\n  justify-content: space-between;\n  gap: 40px;\n  margin-bottom: 30px;\n  padding-bottom: 25px;\n  border-bottom: 2px solid #eee;\n}\n.parties h3 {\n  color: #667eea;\n  text-transform: uppercase;\n  font-size: 14px;\n}\n/* META TABLE */\n.meta table {\n  width: 100%;\n  border-collapse: collapse;\n  margin-bottom: 30px;\n}\n.meta th {\n  background: #667eea;\n  color: white;\n  padding: 12px;\n}\n.meta td {\n  background: #f8f9ff;\n  padding: 12px;\n  text-align: center;\n}\n/* ITEMS TABLE */\ntable {\n  width: 100%;\n  border-collapse: collapse;\n  margin-bottom: 30px;\n}\ntable th {\n  background: linear-gradient(135deg, #667eea, #764ba2);\n  color: white;\n  padding: 14px;\n}\ntable td {\n  border-bottom: 1px solid #eee;\n  padding: 14px;\n}\ntable td:last-child,\ntable th:last-child {\n  text-align: right;\n}\n/* TOTALS */\n.totals {\n  width: 350px;\n  margin-left: auto;\n  margin-top: 20px;\n  padding: 20px;\n  background: #f8f9ff;\n  border-radius: 12px;\n}\n.totals h3 {\n  background: linear-gradient(135deg, #667eea, #764ba2);\n  color: white;\n  padding: 15px;\n  border-radius: 10px;\n  text-align: center;\n}\n/* NOTES */\n.notes {\n  margin-top: 40px;\n  padding: 20px;\n  background: #fffbf0;\n  border-left: 5px solid #ffb300;\n  border-radius: 10px;\n}\n/* FOOTER */\n.footer {\n  text-align: center;\n  margin-top: 40px;\n  padding: 20px;\n  background: #f8f9ff;\n  font-size: 13px;\n  color: #666;\n}\n",
    "html_content": "<!DOCTYPE html>\n<html xmlns=\"http://www.w3.org/1999/xhtml\" lang=\"\" xml:lang=\"\">\n<head>\n  <meta charset=\"utf-8\" />\n  <meta name=\"generator\" content=\"pandoc\" />\n  <meta name=\"viewport\" content=\"width=device-width, initial-scale=1.0, user-scalable=yes\" />\n  <title>-</title>\n  <style>\n    code{white-space: pre-wrap;}\n    span.smallcaps{font-variant: small-caps;}\n    div.columns{display: flex; gap: min(4vw, 1.5em);}\n    div.column{flex: auto; overflow-x: auto;}\n    div.hanging-indent{margin-left: 1.5em; text-indent: -1.5em;}\n    /* The extra [class] is a hack that increases specificity enough to\n       override a similar rule in reveal.js */\n    ul.task-list[class]{list-style: none;}\n    ul.task-list li input[type=\"checkbox\"] {\n      font-size: inherit;\n      width: 0.8em;\n      margin: 0 0.8em 0.2em -1.6em;\n      vertical-align: middle;\n    }\n    .display.math{display: block; text-align: center; margin: 0.5rem auto;}\n  </style>\n  <link rel=\"stylesheet\" href=\"invoice.css\" />\n<style>body {\n  font-family: \"Segoe UI\", system-ui, sans-serif;\n  background: #ffffff;\n  color: #333;\n}\n/* HEADER */\n.invoice-header {\n  background: linear-gradient(135deg, #667eea, #764ba2);\n  color: white;\n  padding: 40px;\n  border-radius: 16px;\n  margin-bottom: 30px;\n}\n.invoice-header h1 {\n  font-size: 32px;\n  margin-bottom: 10px;\n}\n.invoice-header h2 {\n  font-size: 40px;\n  text-align: right;\n}\n/* BILL / SHIP */\n.parties {\n  display: flex;\n  justify-content: space-between;\n  gap: 40px;\n  margin-bottom: 30px;\n  padding-bottom: 25px;\n  border-bottom: 2px solid #eee;\n}\n.parties h3 {\n  color: #667eea;\n  text-transform: uppercase;\n  font-size: 14px;\n}\n/* META TABLE */\n.meta table {\n  width: 100%;\n  border-collapse: collapse;\n  margin-bottom: 30px;\n}\n.meta th {\n  background: #667eea;\n  color: white;\n  padding: 12px;\n}\n.meta td {\n  background: #f8f9ff;\n  padding: 12px;\n  text-align: center;\n}\n/* ITEMS TABLE */\ntable {\n  width: 100%;\n  border-collapse: collapse;\n  margin-bottom: 30px;\n}\ntable th {\n  background: linear-gradient(135deg, #667eea, #764ba2);\n  color: white;\n  padding: 14px;\n}\ntable td {\n  border-bottom: 1px solid #eee;\n  padding: 14px;\n}\ntable td:last-child,\ntable th:last-child {\n  text-align: right;\n}\n/* TOTALS */\n.totals {\n  width: 350px;\n  margin-left: auto;\n  margin-top: 20px;\n  padding: 20px;\n  background: #f8f9ff;\n  border-radius: 12px;\n}\n.totals h3 {\n  background: linear-gradient(135deg, #667eea, #764ba2);\n  color: white;\n  padding: 15px;\n  border-radius: 10px;\n  text-align: center;\n}\n/* NOTES */\n.notes {\n  margin-top: 40px;\n  padding: 20px;\n  background: #fffbf0;\n  border-left: 5px solid #ffb300;\n  border-radius: 10px;\n}\n/* FOOTER */\n.footer {\n  text-align: center;\n  margin-top: 40px;\n  padding: 20px;\n  background: #f8f9ff;\n  font-size: 13px;\n  color: #666;\n}\n</style></head>\n<body>\n<section id=\"your-company-name\" class=\"invoice-header\">\n<h1>Your Company Name</h1>\n<p>Your Street Address<br />\nYour City, State, ZIP, {{company_state}} {{company_zip}}<br />\nYour Email Address<br />\nYour Phone Number</p>\n<p><strong>Invoice No:</strong> INV-INV-2025-12-001234</p>\n</section>\n<hr />\n<div class=\"parties\">\n<h3 id=\"bill-to\">Bill To</h3>\n<p><strong>John Doe</strong><br />\n123 Main Street, Suite 100<br />\nSan Francisco, CA 94105<br />\njohn.doe@example.com</p>\n<hr />\n<h3 id=\"ship-to\">Ship To</h3>\n<p><strong>John Doe</strong><br />\n123 Main Street, Suite 100<br />\nSan Francisco, CA 94105</p>\n<p>Same as billing address</p>\n</div>\n<hr />\n<div class=\"meta\">\n<table>\n<thead>\n<tr class=\"header\">\n<th>Invoice Date</th>\n<th>Due Date</th>\n<th>Payment Terms</th>\n</tr>\n</thead>\n<tbody>\n<tr class=\"odd\">\n<td>2025-12-10</td>\n<td>2026-01-09</td>\n<td>{{payment_terms}}</td>\n</tr>\n</tbody>\n</table>\n</div>\n<hr />\n<h2 id=\"invoice-items\">🧾 Invoice Items</h2>\n<table>\n<thead>\n<tr class=\"header\">\n<th>Description</th>\n<th>Quantity</th>\n<th>Unit Price</th>\n<th>Amount</th>\n</tr>\n</thead>\n<tbody>\n<tr class=\"odd\">\n<td>Premium Plan - Monthly Subscription</td>\n<td>1</td>\n<td>$199.00</td>\n<td>$199.00</td>\n</tr>\n<tr class=\"even\">\n<td>Additional Storage - 100GB</td>\n<td>1</td>\n<td>$50.00</td>\n<td>$50.00</td>\n</tr>\n<tr class=\"odd\">\n<td>API Access - Pro Tier</td>\n<td>1</td>\n<td>$50.00</td>\n<td>$50.00</td>\n</tr>\n</tbody>\n</table>\n<hr />\n<div class=\"totals\">\n<p><strong>Subtotal:</strong> 299<br />\n<strong>Tax (10%):</strong> 29.9</p>\n<h3 id=\"total-due-328.9\"><strong>Total Due: 328.9</strong></h3>\n</div>\n<hr />\n<section id=\"payment-instructions\" class=\"notes\">\n<h3>Payment Instructions</h3>\n<p>Thank you for your business. Payment is due within 30 days.</p>\n</section>\n<hr />\n<div class=\"footer\">\n<p>Thank you for your business!<br />\nFor invoice questions: <strong>Your Email Address</strong></p>\n</div>\n</body>\n</html>\n",
    "is_active": true,
    "is_default": true
  }
]